{
  "projects": [
    {
      "id": 1,
      "title": "Proyecto de Ejemplo",
      "description": "Este es un proyecto de ejemplo",
      "amount": 10,
      "status": "Abierto",
      "clientId": "1",
      "clientName": "Cliente Ejemplo",
      "budget": "10 SOL",
      "duration": "1 mes",
      "skills": ["React", "Node.js"],
      "applications": [],
      "created_at": "2024-03-09T12:00:00Z"
    },
    {
      "id": 2,
      "title": "Aplicación de Gestión de Tareas",
      "description": "Sistema de gestión de tareas con notificaciones en tiempo real y colaboración en equipo.",
      "budget": "$3,000 - $5,000",
      "duration": "2 meses",
      "skills": ["Vue.js", "Firebase", "Tailwind CSS"],
      "status": "En Progreso",
      "clientId": 1,
      "clientName": "Juan Pérez",
      "assignedDeveloper": {
        "id": 3,
        "name": "Carlos Rodríguez"
      }
    }
  ]
} 